MANIFEST.in
README.rst
setup.py
django_mongologging.egg-info/PKG-INFO
django_mongologging.egg-info/SOURCES.txt
django_mongologging.egg-info/dependency_links.txt
django_mongologging.egg-info/requires.txt
django_mongologging.egg-info/top_level.txt
mongologging/__init__.py
mongologging/admin.py
mongologging/apps.py
mongologging/celery.py
mongologging/connection.py
mongologging/decorators.py
mongologging/forms.py
mongologging/middleware.py
mongologging/mixins.py
mongologging/models.py
mongologging/tasks.py
mongologging/tests.py
mongologging/urls.py
mongologging/utils.py
mongologging/views.py
mongologging/http/__init__.py
mongologging/http/constants.py
mongologging/http/decorators.py
mongologging/http/utils.py
mongologging/static/.gitkeep
mongologging/templates/filter.html